{
    "qytete": [{
        "sName": "Spitale",
        "Spitale": [{
            "name": "Tirana",
            "departament": [{
                "dName": "Kardjologjia",
                "pos": {
                    "lat": 45.6585,
                    "lng": 45.86
                }
            }, {
                "dName": "Ortopedia",
                "pos": {
                    "lat": 45.6885,
                    "lng": 45.86
                }
            }, {
                "dName": "Sh. shpejd",
                "pos": {
                    "lat": 45.6685,
                    "lng": 45.86
                }
            }]

        }, {
            "name": "Durres",
            "departament": [{
                "dName": "Kardjologjia",
                "pos": {
                    "lat": 45.65952,
                    "lng": 45.8669
                }
            }, {
                "dName": "Ortopedia",
                "pos": {
                    "lat": 47.6885,
                    "lng": 45.86
                }
            }, {
                "dName": "Sh. shpejd",
                "pos": {
                    "lat": 45.7685,
                    "lng": 45.86
                }
            }]

        }]
    }, {
        "sName": "Kilinika",
        "Kilinika": [{
            "name": "Tirana",
            "departament": [{
                "dName": "Kardjologjia",
                "pos": {
                    "lat": 45.6585,
                    "lng": 45.86
                }
            }, {
                "dName": "Ortopedia",
                "pos": {
                    "lat": 45.6885,
                    "lng": 45.86
                }
            }, {
                "dName": "Sh. shpejd",
                "pos": {
                    "lat": 45.6685,
                    "lng": 45.8
                }
            }]

        }]
    }]


}